collective.upload-1.3b1-py2.7-nspkg.pth
collective/upload/__init__.py
collective/upload/behaviors.py
collective/upload/browser.py
collective/upload/browser.zcml
collective/upload/config.py
collective/upload/configure.zcml
collective/upload/controlpanel.py
collective/upload/interfaces.py
collective/upload/logger.py
collective/upload/menu.py
collective/upload/profiles.zcml
collective/upload/setuphandlers.py
collective/upload/testing.py
collective/upload/viewlets.py
collective/upload/viewlets.zcml
collective/upload/Extensions/Install.py
collective/upload/Extensions/__init__.py
collective/upload/locales/collective.upload.pot
collective/upload/locales/manual.pot
collective/upload/locales/plone.pot
collective/upload/locales/es/LC_MESSAGES/collective.upload.po
collective/upload/locales/es/LC_MESSAGES/plone.po
collective/upload/locales/fi/LC_MESSAGES/collective.upload.po
collective/upload/locales/fi/LC_MESSAGES/plone.po
collective/upload/locales/pt_BR/LC_MESSAGES/collective.upload.po
collective/upload/locales/pt_BR/LC_MESSAGES/plone.po
collective/upload/profiles/default/browserlayer.xml
collective/upload/profiles/default/controlpanel.xml
collective/upload/profiles/default/cssregistry.xml
collective/upload/profiles/default/jsregistry.xml
collective/upload/profiles/default/metadata.xml
collective/upload/profiles/default/registry.xml
collective/upload/profiles/default/rolemap.xml
collective/upload/profiles/uninstall/browserlayer.xml
collective/upload/profiles/uninstall/controlpanel.xml
collective/upload/profiles/uninstall/cssregistry.xml
collective/upload/profiles/uninstall/jsregistry.xml
collective/upload/profiles/uninstall/registry.xml
collective/upload/static/canvas-to-blob.min.js
collective/upload/static/jquery.fileupload-fp.js
collective/upload/static/jquery.fileupload-ui.js
collective/upload/static/jquery.fileupload.js
collective/upload/static/jquery.iframe-transport.js
collective/upload/static/load-image.min.js
collective.upload-1.3b1.dist-info/DESCRIPTION.rst
collective.upload-1.3b1.dist-info/METADATA
collective.upload-1.3b1.dist-info/RECORD
collective.upload-1.3b1.dist-info/WHEEL
collective.upload-1.3b1.dist-info/entry_points.txt
collective.upload-1.3b1.dist-info/metadata.json
collective.upload-1.3b1.dist-info/namespace_packages.txt
collective.upload-1.3b1.dist-info/top_level.txt
