Metadata-Version: 2.0
Name: collective.upload
Version: 1.3b1
Summary: File upload widget for Plone with multiple file selection.
Home-page: https://github.com/collective/collective.upload
Author: OpenMultimedia
Author-email: contacto@openmultimedia.biz
License: UNKNOWN
Keywords: plone jquery upload
Platform: UNKNOWN
Classifier: Development Status :: 4 - Beta
Classifier: Environment :: Web Environment
Classifier: Framework :: Plone
Classifier: Framework :: Plone :: 4.2
Classifier: Framework :: Plone :: 4.3
Classifier: Intended Audience :: End Users/Desktop
Classifier: Intended Audience :: System Administrators
Classifier: License :: OSI Approved :: GNU General Public License v2 (GPLv2)
Classifier: Operating System :: OS Independent
Classifier: Programming Language :: JavaScript
Classifier: Programming Language :: Python
Classifier: Programming Language :: Python :: 2.7
Classifier: Topic :: Software Development :: Libraries :: Python Modules
Requires-Dist: Acquisition
Requires-Dist: Products.ATContentTypes
Requires-Dist: Products.CMFCore
Requires-Dist: Products.CMFPlone (>=4.2,<5.0)
Requires-Dist: Products.GenericSetup
Requires-Dist: plone.api (>=1.4.11)
Requires-Dist: plone.app.content
Requires-Dist: plone.app.contentmenu
Requires-Dist: plone.app.jquery (>=1.7.2)
Requires-Dist: plone.app.jquerytools (>=1.5.7)
Requires-Dist: plone.app.layout
Requires-Dist: plone.app.registry
Requires-Dist: plone.namedfile[blobs]
Requires-Dist: plone.registry
Requires-Dist: setuptools
Requires-Dist: zope.component
Requires-Dist: zope.container
Requires-Dist: zope.event
Requires-Dist: zope.i18n
Requires-Dist: zope.i18nmessageid
Requires-Dist: zope.interface
Requires-Dist: zope.lifecycleevent
Requires-Dist: zope.schema
Provides-Extra: test
Requires-Dist: AccessControl; extra == 'test'
Requires-Dist: plone.app.robotframework; extra == 'test'
Requires-Dist: plone.app.testing[robot]; extra == 'test'
Requires-Dist: plone.browserlayer; extra == 'test'
Requires-Dist: plone.testing; extra == 'test'
Requires-Dist: robotsuite; extra == 'test'
Requires-Dist: transaction; extra == 'test'
Requires-Dist: zope.browsermenu; extra == 'test'
Requires-Dist: zope.viewlet; extra == 'test'
